[[{"location":"C:\\Program Files\\Java\\jre-10.0.2","type":"JRE","hints":{"EXECUTION_ENVIRONMENT":"J2SE-1.5"}},"jre:jre:1.5.0"],[{"location":"C:\\Users\\arune\\.m2\\repository\\org\\hibernate\\hibernate-core\\4.3.11.Final\\hibernate-core-4.3.11.Final.jar","type":"JAR","hints":{}},"org.hibernate.core:org.hibernate.core:4.3.11"],[{"location":"C:\\Users\\arune\\OneDrive\\Desktop\\CTS_FSD\\Eclipse_FSD_files\\Maven\\Maven_SQL_Mappings","type":"PROJECT","hints":{"PROJECT_NAME":"Maven_SQL_Mappings"}},"com:Maven_SQL_Mappings:0.0.1"]]